{
  "$schema": "https://schema.management.azure.com/schemas/2019-04-01/deploymentTemplate.json#",
  "contentVersion": "1.0.0.0",
  "metadata": {
    "_generator": {
      "name": "bicep",
      "version": "0.21.1.54444",
      "templateHash": "5043907679276521852"
    },
    "name": "Azure Active Directory Domain Services",
    "description": "This module deploys an Azure Active Directory Domain Services (AADDS).",
    "owner": "Azure/module-maintainers"
  },
  "parameters": {
    "name": {
      "type": "string",
      "defaultValue": "[parameters('domainName')]",
      "metadata": {
        "description": "Optional. The name of the AADDS resource. Defaults to the domain name specific to the Azure ADDS service."
      }
    },
    "domainName": {
      "type": "string",
      "metadata": {
        "description": "Required. The domain name specific to the Azure ADDS service."
      }
    },
    "sku": {
      "type": "string",
      "defaultValue": "Standard",
      "allowedValues": [
        "Standard",
        "Enterprise",
        "Premium"
      ],
      "metadata": {
        "description": "Optional. The name of the SKU specific to Azure ADDS Services."
      }
    },
    "location": {
      "type": "string",
      "defaultValue": "[resourceGroup().location]",
      "metadata": {
        "description": "Optional. The location to deploy the Azure ADDS Services."
      }
    },
    "replicaSets": {
      "type": "array",
      "defaultValue": [],
      "metadata": {
        "description": "Optional. Additional replica set for the managed domain."
      }
    },
    "pfxCertificate": {
      "type": "securestring",
      "defaultValue": "",
      "metadata": {
        "description": "Conditional. The certificate required to configure Secure LDAP. Should be a base64encoded representation of the certificate PFX file. Required if secure LDAP is enabled and must be valid more than 30 days."
      }
    },
    "pfxCertificatePassword": {
      "type": "securestring",
      "defaultValue": "",
      "metadata": {
        "description": "Conditional. The password to decrypt the provided Secure LDAP certificate PFX file. Required if secure LDAP is enabled."
      }
    },
    "additionalRecipients": {
      "type": "array",
      "defaultValue": [],
      "metadata": {
        "description": "Optional. The email recipient value to receive alerts."
      }
    },
    "domainConfigurationType": {
      "type": "string",
      "defaultValue": "FullySynced",
      "allowedValues": [
        "FullySynced",
        "ResourceTrusting"
      ],
      "metadata": {
        "description": "Optional. The value is to provide domain configuration type."
      }
    },
    "filteredSync": {
      "type": "string",
      "defaultValue": "Enabled",
      "metadata": {
        "description": "Optional. The value is to synchronize scoped users and groups."
      }
    },
    "tlsV1": {
      "type": "string",
      "defaultValue": "Enabled",
      "allowedValues": [
        "Enabled",
        "Disabled"
      ],
      "metadata": {
        "description": "Optional. The value is to enable clients making request using TLSv1."
      }
    },
    "ntlmV1": {
      "type": "string",
      "defaultValue": "Enabled",
      "allowedValues": [
        "Enabled",
        "Disabled"
      ],
      "metadata": {
        "description": "Optional. The value is to enable clients making request using NTLM v1."
      }
    },
    "syncNtlmPasswords": {
      "type": "string",
      "defaultValue": "Enabled",
      "allowedValues": [
        "Enabled",
        "Disabled"
      ],
      "metadata": {
        "description": "Optional. The value is to enable synchronized users to use NTLM authentication."
      }
    },
    "syncOnPremPasswords": {
      "type": "string",
      "defaultValue": "Enabled",
      "allowedValues": [
        "Enabled",
        "Disabled"
      ],
      "metadata": {
        "description": "Optional. The value is to enable on-premises users to authenticate against managed domain."
      }
    },
    "kerberosRc4Encryption": {
      "type": "string",
      "defaultValue": "Enabled",
      "allowedValues": [
        "Enabled",
        "Disabled"
      ],
      "metadata": {
        "description": "Optional. The value is to enable Kerberos requests that use RC4 encryption."
      }
    },
    "kerberosArmoring": {
      "type": "string",
      "defaultValue": "Enabled",
      "allowedValues": [
        "Enabled",
        "Disabled"
      ],
      "metadata": {
        "description": "Optional. The value is to enable to provide a protected channel between the Kerberos client and the KDC."
      }
    },
    "notifyDcAdmins": {
      "type": "string",
      "defaultValue": "Enabled",
      "allowedValues": [
        "Enabled",
        "Disabled"
      ],
      "metadata": {
        "description": "Optional. The value is to notify the DC Admins."
      }
    },
    "notifyGlobalAdmins": {
      "type": "string",
      "defaultValue": "Enabled",
      "allowedValues": [
        "Enabled",
        "Disabled"
      ],
      "metadata": {
        "description": "Optional. The value is to notify the Global Admins."
      }
    },
    "externalAccess": {
      "type": "string",
      "defaultValue": "Enabled",
      "allowedValues": [
        "Enabled",
        "Disabled"
      ],
      "metadata": {
        "description": "Optional. The value is to enable the Secure LDAP for external services of Azure ADDS Services."
      }
    },
    "ldaps": {
      "type": "string",
      "defaultValue": "Enabled",
      "allowedValues": [
        "Enabled",
        "Disabled"
      ],
      "metadata": {
        "description": "Optional. A flag to determine whether or not Secure LDAP is enabled or disabled."
      }
    },
    "diagnosticStorageAccountId": {
      "type": "string",
      "defaultValue": "",
      "metadata": {
        "description": "Optional. Resource ID of the diagnostic storage account."
      }
    },
    "diagnosticWorkspaceId": {
      "type": "string",
      "defaultValue": "",
      "metadata": {
        "description": "Optional. Resource ID of the diagnostic log analytics workspace."
      }
    },
    "diagnosticEventHubAuthorizationRuleId": {
      "type": "string",
      "defaultValue": "",
      "metadata": {
        "description": "Optional. Resource ID of the diagnostic event hub authorization rule for the Event Hubs namespace in which the event hub should be created or streamed to."
      }
    },
    "diagnosticEventHubName": {
      "type": "string",
      "defaultValue": "",
      "metadata": {
        "description": "Optional. Name of the diagnostic event hub within the namespace to which logs are streamed. Without this, an event hub is created for each log category."
      }
    },
    "tags": {
      "type": "object",
      "defaultValue": {},
      "metadata": {
        "description": "Optional. Tags of the resource."
      }
    },
    "enableDefaultTelemetry": {
      "type": "bool",
      "defaultValue": true,
      "metadata": {
        "description": "Optional. Enable telemetry via a Globally Unique Identifier (GUID)."
      }
    },
    "lock": {
      "type": "string",
      "defaultValue": "",
      "allowedValues": [
        "",
        "CanNotDelete",
        "ReadOnly"
      ],
      "metadata": {
        "description": "Optional. Specify the type of lock."
      }
    },
    "roleAssignments": {
      "type": "array",
      "defaultValue": [],
      "metadata": {
        "description": "Optional. Array of role assignment objects that contain the 'roleDefinitionIdOrName' and 'principalId' to define RBAC role assignments on this resource. In the roleDefinitionIdOrName attribute, you can provide either the display name of the role definition, or its fully qualified ID in the following format: '/providers/Microsoft.Authorization/roleDefinitions/c2f4ef07-c644-48eb-af81-4b1b4947fb11'."
      }
    },
    "diagnosticLogCategoriesToEnable": {
      "type": "array",
      "defaultValue": [
        "allLogs"
      ],
      "allowedValues": [
        "",
        "allLogs",
        "SystemSecurity",
        "AccountManagement",
        "LogonLogoff",
        "ObjectAccess",
        "PolicyChange",
        "PrivilegeUse",
        "DetailTracking",
        "DirectoryServiceAccess",
        "AccountLogon"
      ],
      "metadata": {
        "description": "Optional. The name of logs that will be streamed. \"allLogs\" includes all possible logs for the resource. Set to '' to disable log collection."
      }
    }
  },
  "variables": {
    "copy": [
      {
        "name": "diagnosticsLogsSpecified",
        "count": "[length(filter(parameters('diagnosticLogCategoriesToEnable'), lambda('item', and(not(equals(lambdaVariables('item'), 'allLogs')), not(equals(lambdaVariables('item'), ''))))))]",
        "input": {
          "category": "[filter(parameters('diagnosticLogCategoriesToEnable'), lambda('item', and(not(equals(lambdaVariables('item'), 'allLogs')), not(equals(lambdaVariables('item'), '')))))[copyIndex('diagnosticsLogsSpecified')]]",
          "enabled": true
        }
      }
    ],
    "diagnosticsLogs": "[if(contains(parameters('diagnosticLogCategoriesToEnable'), 'allLogs'), createArray(createObject('categoryGroup', 'allLogs', 'enabled', true())), if(contains(parameters('diagnosticLogCategoriesToEnable'), ''), createArray(), variables('diagnosticsLogsSpecified')))]"
  },
  "resources": [
    {
      "condition": "[parameters('enableDefaultTelemetry')]",
      "type": "Microsoft.Resources/deployments",
      "apiVersion": "2021-04-01",
      "name": "[format('pid-47ed15a6-730a-4827-bcb4-0fd963ffbd82-{0}', uniqueString(deployment().name))]",
      "properties": {
        "mode": "Incremental",
        "template": {
          "$schema": "https://schema.management.azure.com/schemas/2019-04-01/deploymentTemplate.json#",
          "contentVersion": "1.0.0.0",
          "resources": []
        }
      }
    },
    {
      "type": "Microsoft.AAD/domainServices",
      "apiVersion": "2021-05-01",
      "name": "[parameters('name')]",
      "location": "[parameters('location')]",
      "tags": "[parameters('tags')]",
      "properties": {
        "domainName": "[parameters('domainName')]",
        "domainConfigurationType": "[parameters('domainConfigurationType')]",
        "filteredSync": "[parameters('filteredSync')]",
        "notificationSettings": {
          "additionalRecipients": "[parameters('additionalRecipients')]",
          "notifyDcAdmins": "[parameters('notifyDcAdmins')]",
          "notifyGlobalAdmins": "[parameters('notifyGlobalAdmins')]"
        },
        "ldapsSettings": {
          "externalAccess": "[parameters('externalAccess')]",
          "ldaps": "[parameters('ldaps')]",
          "pfxCertificate": "[if(not(empty(parameters('pfxCertificate'))), parameters('pfxCertificate'), null())]",
          "pfxCertificatePassword": "[if(not(empty(parameters('pfxCertificatePassword'))), parameters('pfxCertificatePassword'), null())]"
        },
        "replicaSets": "[parameters('replicaSets')]",
        "domainSecuritySettings": {
          "tlsV1": "[parameters('tlsV1')]",
          "ntlmV1": "[parameters('ntlmV1')]",
          "syncNtlmPasswords": "[parameters('syncNtlmPasswords')]",
          "syncOnPremPasswords": "[parameters('syncOnPremPasswords')]",
          "kerberosRc4Encryption": "[parameters('kerberosRc4Encryption')]",
          "kerberosArmoring": "[parameters('kerberosArmoring')]"
        },
        "sku": "[parameters('sku')]"
      }
    },
    {
      "condition": "[or(or(or(not(empty(parameters('diagnosticStorageAccountId'))), not(empty(parameters('diagnosticWorkspaceId')))), not(empty(parameters('diagnosticEventHubAuthorizationRuleId')))), not(empty(parameters('diagnosticEventHubName'))))]",
      "type": "Microsoft.Insights/diagnosticSettings",
      "apiVersion": "2021-05-01-preview",
      "scope": "[format('Microsoft.AAD/domainServices/{0}', parameters('name'))]",
      "name": "[format('{0}-diagnosticSettings', parameters('name'))]",
      "properties": {
        "storageAccountId": "[if(not(empty(parameters('diagnosticStorageAccountId'))), parameters('diagnosticStorageAccountId'), null())]",
        "workspaceId": "[if(not(empty(parameters('diagnosticWorkspaceId'))), parameters('diagnosticWorkspaceId'), null())]",
        "eventHubAuthorizationRuleId": "[if(not(empty(parameters('diagnosticEventHubAuthorizationRuleId'))), parameters('diagnosticEventHubAuthorizationRuleId'), null())]",
        "eventHubName": "[if(not(empty(parameters('diagnosticEventHubName'))), parameters('diagnosticEventHubName'), null())]",
        "logs": "[variables('diagnosticsLogs')]"
      },
      "dependsOn": [
        "[resourceId('Microsoft.AAD/domainServices', parameters('name'))]"
      ]
    },
    {
      "condition": "[not(empty(parameters('lock')))]",
      "type": "Microsoft.Authorization/locks",
      "apiVersion": "2020-05-01",
      "scope": "[format('Microsoft.AAD/domainServices/{0}', parameters('name'))]",
      "name": "[format('{0}-{1}-lock', parameters('name'), parameters('lock'))]",
      "properties": {
        "level": "[parameters('lock')]",
        "notes": "[if(equals(parameters('lock'), 'CanNotDelete'), 'Cannot delete resource or child resources.', 'Cannot modify the resource or child resources.')]"
      },
      "dependsOn": [
        "[resourceId('Microsoft.AAD/domainServices', parameters('name'))]"
      ]
    },
    {
      "copy": {
        "name": "domainService_roleAssignments",
        "count": "[length(parameters('roleAssignments'))]"
      },
      "type": "Microsoft.Resources/deployments",
      "apiVersion": "2022-09-01",
      "name": "[format('{0}-VNet-Rbac-{1}', uniqueString(deployment().name, parameters('location')), copyIndex())]",
      "properties": {
        "expressionEvaluationOptions": {
          "scope": "inner"
        },
        "mode": "Incremental",
        "parameters": {
          "description": "[if(contains(parameters('roleAssignments')[copyIndex()], 'description'), createObject('value', parameters('roleAssignments')[copyIndex()].description), createObject('value', ''))]",
          "principalIds": {
            "value": "[parameters('roleAssignments')[copyIndex()].principalIds]"
          },
          "principalType": "[if(contains(parameters('roleAssignments')[copyIndex()], 'principalType'), createObject('value', parameters('roleAssignments')[copyIndex()].principalType), createObject('value', ''))]",
          "roleDefinitionIdOrName": {
            "value": "[parameters('roleAssignments')[copyIndex()].roleDefinitionIdOrName]"
          },
          "condition": "[if(contains(parameters('roleAssignments')[copyIndex()], 'condition'), createObject('value', parameters('roleAssignments')[copyIndex()].condition), createObject('value', ''))]",
          "delegatedManagedIdentityResourceId": "[if(contains(parameters('roleAssignments')[copyIndex()], 'delegatedManagedIdentityResourceId'), createObject('value', parameters('roleAssignments')[copyIndex()].delegatedManagedIdentityResourceId), createObject('value', ''))]",
          "resourceId": {
            "value": "[resourceId('Microsoft.AAD/domainServices', parameters('name'))]"
          }
        },
        "template": {
          "$schema": "https://schema.management.azure.com/schemas/2019-04-01/deploymentTemplate.json#",
          "contentVersion": "1.0.0.0",
          "metadata": {
            "_generator": {
              "name": "bicep",
              "version": "0.21.1.54444",
              "templateHash": "4015790044658504688"
            }
          },
          "parameters": {
            "principalIds": {
              "type": "array",
              "metadata": {
                "description": "Required. The IDs of the principals to assign the role to."
              }
            },
            "roleDefinitionIdOrName": {
              "type": "string",
              "metadata": {
                "description": "Required. The name of the role to assign. If it cannot be found you can specify the role definition ID instead."
              }
            },
            "resourceId": {
              "type": "string",
              "metadata": {
                "description": "Required. The resource ID of the resource to apply the role assignment to."
              }
            },
            "principalType": {
              "type": "string",
              "defaultValue": "",
              "allowedValues": [
                "ServicePrincipal",
                "Group",
                "User",
                "ForeignGroup",
                "Device",
                ""
              ],
              "metadata": {
                "description": "Optional. The principal type of the assigned principal ID."
              }
            },
            "description": {
              "type": "string",
              "defaultValue": "",
              "metadata": {
                "description": "Optional. The description of the role assignment."
              }
            },
            "condition": {
              "type": "string",
              "defaultValue": "",
              "metadata": {
                "description": "Optional. The conditions on the role assignment. This limits the resources it can be assigned to. e.g.: @Resource[Microsoft.Storage/storageAccounts/blobServices/containers:ContainerName] StringEqualsIgnoreCase \"foo_storage_container\"."
              }
            },
            "conditionVersion": {
              "type": "string",
              "defaultValue": "2.0",
              "allowedValues": [
                "2.0"
              ],
              "metadata": {
                "description": "Optional. Version of the condition."
              }
            },
            "delegatedManagedIdentityResourceId": {
              "type": "string",
              "defaultValue": "",
              "metadata": {
                "description": "Optional. Id of the delegated managed identity resource."
              }
            }
          },
          "variables": {
            "builtInRoleNames": {
              "Contributor": "[subscriptionResourceId('Microsoft.Authorization/roleDefinitions', 'b24988ac-6180-42a0-ab88-20f7382dd24c')]",
              "Domain Services Contributor": "[subscriptionResourceId('Microsoft.Authorization/roleDefinitions', 'eeaeda52-9324-47f6-8069-5d5bade478b2')]",
              "Domain Services Reader": "[subscriptionResourceId('Microsoft.Authorization/roleDefinitions', '361898ef-9ed1-48c2-849c-a832951106bb')]",
              "HDInsight Domain Services Contributor": "[subscriptionResourceId('Microsoft.Authorization/roleDefinitions', '8d8d5a11-05d3-4bda-a417-a08778121c7c')]",
              "Log Analytics Contributor": "[subscriptionResourceId('Microsoft.Authorization/roleDefinitions', '92aaf0da-9dab-42b6-94a3-d43ce8d16293')]",
              "Log Analytics Reader": "[subscriptionResourceId('Microsoft.Authorization/roleDefinitions', '73c42c96-874c-492b-b04d-ab87d138a893')]",
              "Managed Application Contributor Role": "[subscriptionResourceId('Microsoft.Authorization/roleDefinitions', '641177b8-a67a-45b9-a033-47bc880bb21e')]",
              "Managed Application Operator Role": "[subscriptionResourceId('Microsoft.Authorization/roleDefinitions', 'c7393b34-138c-406f-901b-d8cf2b17e6ae')]",
              "Managed Applications Reader": "[subscriptionResourceId('Microsoft.Authorization/roleDefinitions', 'b9331d33-8a36-4f8c-b097-4f54124fdb44')]",
              "Monitoring Contributor": "[subscriptionResourceId('Microsoft.Authorization/roleDefinitions', '749f88d5-cbae-40b8-bcfc-e573ddc772fa')]",
              "Monitoring Reader": "[subscriptionResourceId('Microsoft.Authorization/roleDefinitions', '43d0d8ad-25c7-4714-9337-8ba259a9fe05')]",
              "Owner": "[subscriptionResourceId('Microsoft.Authorization/roleDefinitions', '8e3af657-a8ff-443c-a75c-2fe8c4bcb635')]",
              "Reader": "[subscriptionResourceId('Microsoft.Authorization/roleDefinitions', 'acdd72a7-3385-48ef-bd42-f606fba81ae7')]",
              "Resource Policy Contributor": "[subscriptionResourceId('Microsoft.Authorization/roleDefinitions', '36243c78-bf99-498c-9df9-86d9f8d28608')]",
              "Role Based Access Control Administrator (Preview)": "[subscriptionResourceId('Microsoft.Authorization/roleDefinitions', 'f58310d9-a9f6-439a-9e8d-f62e7b41a168')]",
              "User Access Administrator": "[subscriptionResourceId('Microsoft.Authorization/roleDefinitions', '18d7d88d-d35e-4fb5-a5c3-7773c20a72d9')]"
            }
          },
          "resources": [
            {
              "copy": {
                "name": "roleAssignment",
                "count": "[length(parameters('principalIds'))]"
              },
              "type": "Microsoft.Authorization/roleAssignments",
              "apiVersion": "2022-04-01",
              "scope": "[format('Microsoft.AAD/domainServices/{0}', last(split(parameters('resourceId'), '/')))]",
              "name": "[guid(resourceId('Microsoft.AAD/domainServices', last(split(parameters('resourceId'), '/'))), parameters('principalIds')[copyIndex()], parameters('roleDefinitionIdOrName'))]",
              "properties": {
                "description": "[parameters('description')]",
                "roleDefinitionId": "[if(contains(variables('builtInRoleNames'), parameters('roleDefinitionIdOrName')), variables('builtInRoleNames')[parameters('roleDefinitionIdOrName')], parameters('roleDefinitionIdOrName'))]",
                "principalId": "[parameters('principalIds')[copyIndex()]]",
                "principalType": "[if(not(empty(parameters('principalType'))), parameters('principalType'), null())]",
                "condition": "[if(not(empty(parameters('condition'))), parameters('condition'), null())]",
                "conditionVersion": "[if(and(not(empty(parameters('conditionVersion'))), not(empty(parameters('condition')))), parameters('conditionVersion'), null())]",
                "delegatedManagedIdentityResourceId": "[if(not(empty(parameters('delegatedManagedIdentityResourceId'))), parameters('delegatedManagedIdentityResourceId'), null())]"
              }
            }
          ]
        }
      },
      "dependsOn": [
        "[resourceId('Microsoft.AAD/domainServices', parameters('name'))]"
      ]
    }
  ],
  "outputs": {
    "name": {
      "type": "string",
      "metadata": {
        "description": "The domain name of the Azure Active Directory Domain Services(Azure ADDS)."
      },
      "value": "[parameters('name')]"
    },
    "resourceGroupName": {
      "type": "string",
      "metadata": {
        "description": "The name of the resource group the Azure Active Directory Domain Services(Azure ADDS) was created in."
      },
      "value": "[resourceGroup().name]"
    },
    "resourceId": {
      "type": "string",
      "metadata": {
        "description": "The resource ID of the Azure Active Directory Domain Services(Azure ADDS)."
      },
      "value": "[resourceId('Microsoft.AAD/domainServices', parameters('name'))]"
    },
    "location": {
      "type": "string",
      "metadata": {
        "description": "The location the resource was deployed into."
      },
      "value": "[reference(resourceId('Microsoft.AAD/domainServices', parameters('name')), '2021-05-01', 'full').location]"
    }
  }
}